nikkiepy/__init__.py
nikkiepy/crypt.py
nikkiepy/files.py
nikkiepy/sockets.py
nikkiepy-0.3.0.dist-info/METADATA
nikkiepy-0.3.0.dist-info/WHEEL
nikkiepy-0.3.0.dist-info/top_level.txt
nikkiepy-0.3.0.dist-info/RECORD
