Metadata-Version: 2.1
Name: nikkiepy
Version: 0.3.0
Summary: Custom python library by: NikkieDev
Home-page: https://github.com/NikkieCodes/nikkiepy
Author: NikkieDev#6322
Author-email: nikkieschaad@gmail.com
License: UNKNOWN
Platform: UNKNOWN
Requires-Python: >=3.7
